griptape/__init__.py
griptape/artifacts/__init__.py
griptape/artifacts/action_artifact.py
griptape/artifacts/audio_artifact.py
griptape/artifacts/audio_url_artifact.py
griptape/artifacts/base_artifact.py
griptape/artifacts/blob_artifact.py
griptape/artifacts/boolean_artifact.py
griptape/artifacts/error_artifact.py
griptape/artifacts/generic_artifact.py
griptape/artifacts/image_artifact.py
griptape/artifacts/image_url_artifact.py
griptape/artifacts/info_artifact.py
griptape/artifacts/json_artifact.py
griptape/artifacts/list_artifact.py
griptape/artifacts/model_artifact.py
griptape/artifacts/text_artifact.py
griptape/artifacts/url_artifact.py
griptape/artifacts/video_url_artifact.py
griptape/chunkers/__init__.py
griptape/chunkers/base_chunker.py
griptape/chunkers/chunk_separator.py
griptape/chunkers/markdown_chunker.py
griptape/chunkers/pdf_chunker.py
griptape/chunkers/text_chunker.py
griptape/common/__init__.py
griptape/common/decorators.py
griptape/common/observable.py
griptape/common/reference.py
griptape/common/actions/__init__.py
griptape/common/actions/base_action.py
griptape/common/actions/tool_action.py
griptape/common/prompt_stack/__init__.py
griptape/common/prompt_stack/prompt_stack.py
griptape/common/prompt_stack/contents/__init__.py
griptape/common/prompt_stack/contents/action_call_delta_message_content.py
griptape/common/prompt_stack/contents/action_call_message_content.py
griptape/common/prompt_stack/contents/action_result_message_content.py
griptape/common/prompt_stack/contents/audio_delta_message_content.py
griptape/common/prompt_stack/contents/audio_message_content.py
griptape/common/prompt_stack/contents/base_delta_message_content.py
griptape/common/prompt_stack/contents/base_message_content.py
griptape/common/prompt_stack/contents/generic_message_content.py
griptape/common/prompt_stack/contents/image_message_content.py
griptape/common/prompt_stack/contents/text_delta_message_content.py
griptape/common/prompt_stack/contents/text_message_content.py
griptape-1.8.8.dist-info/METADATA
griptape-1.8.8.dist-info/WHEEL
griptape-1.8.8.dist-info/licenses/LICENSE
griptape-1.8.8.dist-info/licenses/NOTICE
griptape-1.8.8.dist-info/RECORD
