Metadata-Version: 2.4
Name: griptape
Version: 1.8.8
Summary: Modular Python framework for LLM workflows, tools, memory, and data.
Project-URL: Repository, https://github.com/griptape-ai/griptape
Author-email: Griptape <hello@griptape.ai>
License-Expression: Apache-2.0
License-File: LICENSE
License-File: NOTICE
Requires-Python: <4,>=3.9
Requires-Dist: attrs>=24.3.0
Requires-Dist: filetype>=1.2
Requires-Dist: jinja2>=3.1.4
Requires-Dist: marshmallow-enum>=1.5.1
Requires-Dist: marshmallow<4,>=3.21.3
Requires-Dist: numpy<3,>=1.26.4
Requires-Dist: openai>=1.1.1
Requires-Dist: pip>=25.0.1
Requires-Dist: pydantic>=2.7.4
Requires-Dist: pyyaml>=6.0.1
Requires-Dist: requests>=2.32.0
Requires-Dist: rich>=13.7.1
Requires-Dist: schema>=0.7.7
Requires-Dist: tenacity>=8.5.0
Requires-Dist: tiktoken>=0.11
Requires-Dist: urllib3!=2.2.0,<3,>=1.25.4
Requires-Dist: wrapt>=1.16.0
Provides-Extra: all
Requires-Dist: anthropic>=0.45.1; extra == 'all'
Requires-Dist: astrapy>=1.4; extra == 'all'
Requires-Dist: beautifulsoup4>=4.12.3; extra == 'all'
Requires-Dist: boto3>=1.34.119; extra == 'all'
Requires-Dist: cohere>=5.11.2; extra == 'all'
Requires-Dist: diffusers>=0.32.0; extra == 'all'
Requires-Dist: duckduckgo-search>=7.0.1; extra == 'all'
Requires-Dist: elevenlabs>=1.1.2; extra == 'all'
Requires-Dist: exa-py>=1.1.4; extra == 'all'
Requires-Dist: google-generativeai>=0.8.2; extra == 'all'
Requires-Dist: huggingface-hub>=0.28.1; extra == 'all'
Requires-Dist: mail-parser>=4.0.0; extra == 'all'
Requires-Dist: markdownify>=1.0.0; extra == 'all'
Requires-Dist: marqo>=3.9.2; extra == 'all'
Requires-Dist: ollama>=0.4.1; extra == 'all'
Requires-Dist: opensearch-py>=2.3.1; extra == 'all'
Requires-Dist: opentelemetry-api>=1.25.0; extra == 'all'
Requires-Dist: opentelemetry-exporter-otlp-proto-http>=1.25.0; extra == 'all'
Requires-Dist: opentelemetry-instrumentation-threading>=0.49b2; extra == 'all'
Requires-Dist: opentelemetry-instrumentation>=0.49b2; extra == 'all'
Requires-Dist: opentelemetry-sdk>=1.25.0; extra == 'all'
Requires-Dist: pandas>=2.2; extra == 'all'
Requires-Dist: pgvector>=0.3.4; extra == 'all'
Requires-Dist: pillow>=11.0.0; extra == 'all'
Requires-Dist: pinecone>=6.0.1; extra == 'all'
Requires-Dist: playwright>=1.42; extra == 'all'
Requires-Dist: psycopg2-binary>=2.9.9; extra == 'all'
Requires-Dist: pusher>=3.3.2; extra == 'all'
Requires-Dist: pymongo>=4.8.0; extra == 'all'
Requires-Dist: pypdf>=5.0.1; extra == 'all'
Requires-Dist: qdrant-client>=1.10.1; extra == 'all'
Requires-Dist: redis>=5.1.0; extra == 'all'
Requires-Dist: snowflake-sqlalchemy>=1.6.1; extra == 'all'
Requires-Dist: snowflake>=1.0.5; extra == 'all'
Requires-Dist: sqlalchemy>=2.0.31; extra == 'all'
Requires-Dist: tavily-python>=0.5.0; extra == 'all'
Requires-Dist: trafilatura>=2.0; extra == 'all'
Requires-Dist: transformers>=4.41.1; extra == 'all'
Requires-Dist: voyageai>=0.2.1; extra == 'all'
Provides-Extra: drivers-embedding-amazon-bedrock
Requires-Dist: boto3>=1.34.119; extra == 'drivers-embedding-amazon-bedrock'
Provides-Extra: drivers-embedding-amazon-sagemaker
Requires-Dist: boto3>=1.34.119; extra == 'drivers-embedding-amazon-sagemaker'
Provides-Extra: drivers-embedding-cohere
Requires-Dist: cohere>=5.11.2; extra == 'drivers-embedding-cohere'
Provides-Extra: drivers-embedding-google
Requires-Dist: google-generativeai>=0.8.2; extra == 'drivers-embedding-google'
Provides-Extra: drivers-embedding-huggingface
Requires-Dist: huggingface-hub>=0.28.1; extra == 'drivers-embedding-huggingface'
Requires-Dist: transformers>=4.41.1; extra == 'drivers-embedding-huggingface'
Provides-Extra: drivers-embedding-ollama
Requires-Dist: ollama>=0.4.1; extra == 'drivers-embedding-ollama'
Provides-Extra: drivers-embedding-voyageai
Requires-Dist: voyageai>=0.2.1; extra == 'drivers-embedding-voyageai'
Provides-Extra: drivers-event-listener-amazon-iot
Requires-Dist: boto3>=1.34.119; extra == 'drivers-event-listener-amazon-iot'
Provides-Extra: drivers-event-listener-amazon-sqs
Requires-Dist: boto3>=1.34.119; extra == 'drivers-event-listener-amazon-sqs'
Provides-Extra: drivers-event-listener-pusher
Requires-Dist: pusher>=3.3.2; extra == 'drivers-event-listener-pusher'
Provides-Extra: drivers-file-manager-amazon-s3
Requires-Dist: boto3>=1.34.119; extra == 'drivers-file-manager-amazon-s3'
Provides-Extra: drivers-image-generation-huggingface
Requires-Dist: diffusers>=0.32.0; extra == 'drivers-image-generation-huggingface'
Requires-Dist: pillow>=11.0.0; extra == 'drivers-image-generation-huggingface'
Provides-Extra: drivers-memory-conversation-amazon-dynamodb
Requires-Dist: boto3>=1.34.119; extra == 'drivers-memory-conversation-amazon-dynamodb'
Provides-Extra: drivers-memory-conversation-redis
Requires-Dist: redis>=5.1.0; extra == 'drivers-memory-conversation-redis'
Provides-Extra: drivers-observability-datadog
Requires-Dist: opentelemetry-api>=1.25.0; extra == 'drivers-observability-datadog'
Requires-Dist: opentelemetry-exporter-otlp-proto-http>=1.25.0; extra == 'drivers-observability-datadog'
Requires-Dist: opentelemetry-instrumentation-threading>=0.49b2; extra == 'drivers-observability-datadog'
Requires-Dist: opentelemetry-instrumentation>=0.49b2; extra == 'drivers-observability-datadog'
Requires-Dist: opentelemetry-sdk>=1.25.0; extra == 'drivers-observability-datadog'
Provides-Extra: drivers-observability-griptape-cloud
Requires-Dist: opentelemetry-api>=1.25.0; extra == 'drivers-observability-griptape-cloud'
Requires-Dist: opentelemetry-exporter-otlp-proto-http>=1.25.0; extra == 'drivers-observability-griptape-cloud'
Requires-Dist: opentelemetry-instrumentation-threading>=0.49b2; extra == 'drivers-observability-griptape-cloud'
Requires-Dist: opentelemetry-instrumentation>=0.49b2; extra == 'drivers-observability-griptape-cloud'
Requires-Dist: opentelemetry-sdk>=1.25.0; extra == 'drivers-observability-griptape-cloud'
Provides-Extra: drivers-observability-opentelemetry
Requires-Dist: opentelemetry-api>=1.25.0; extra == 'drivers-observability-opentelemetry'
Requires-Dist: opentelemetry-exporter-otlp-proto-http>=1.25.0; extra == 'drivers-observability-opentelemetry'
Requires-Dist: opentelemetry-instrumentation-threading>=0.49b2; extra == 'drivers-observability-opentelemetry'
Requires-Dist: opentelemetry-instrumentation>=0.49b2; extra == 'drivers-observability-opentelemetry'
Requires-Dist: opentelemetry-sdk>=1.25.0; extra == 'drivers-observability-opentelemetry'
Provides-Extra: drivers-prompt-amazon-bedrock
Requires-Dist: anthropic>=0.45.1; extra == 'drivers-prompt-amazon-bedrock'
Requires-Dist: boto3>=1.34.119; extra == 'drivers-prompt-amazon-bedrock'
Provides-Extra: drivers-prompt-amazon-sagemaker
Requires-Dist: boto3>=1.34.119; extra == 'drivers-prompt-amazon-sagemaker'
Requires-Dist: transformers>=4.41.1; extra == 'drivers-prompt-amazon-sagemaker'
Provides-Extra: drivers-prompt-anthropic
Requires-Dist: anthropic>=0.45.1; extra == 'drivers-prompt-anthropic'
Provides-Extra: drivers-prompt-cohere
Requires-Dist: cohere>=5.11.2; extra == 'drivers-prompt-cohere'
Provides-Extra: drivers-prompt-google
Requires-Dist: google-generativeai>=0.8.2; extra == 'drivers-prompt-google'
Provides-Extra: drivers-prompt-huggingface-hub
Requires-Dist: huggingface-hub>=0.28.1; extra == 'drivers-prompt-huggingface-hub'
Requires-Dist: transformers>=4.41.1; extra == 'drivers-prompt-huggingface-hub'
Provides-Extra: drivers-prompt-huggingface-pipeline
Requires-Dist: transformers>=4.41.1; extra == 'drivers-prompt-huggingface-pipeline'
Provides-Extra: drivers-prompt-ollama
Requires-Dist: ollama>=0.4.1; extra == 'drivers-prompt-ollama'
Provides-Extra: drivers-rerank-cohere
Requires-Dist: cohere>=5.11.2; extra == 'drivers-rerank-cohere'
Provides-Extra: drivers-sql
Requires-Dist: sqlalchemy>=2.0.31; extra == 'drivers-sql'
Provides-Extra: drivers-sql-amazon-redshift
Requires-Dist: boto3>=1.34.119; extra == 'drivers-sql-amazon-redshift'
Provides-Extra: drivers-sql-snowflake
Requires-Dist: snowflake-sqlalchemy>=1.6.1; extra == 'drivers-sql-snowflake'
Requires-Dist: snowflake>=1.0.5; extra == 'drivers-sql-snowflake'
Requires-Dist: sqlalchemy>=2.0.31; extra == 'drivers-sql-snowflake'
Provides-Extra: drivers-text-to-speech-elevenlabs
Requires-Dist: elevenlabs>=1.1.2; extra == 'drivers-text-to-speech-elevenlabs'
Provides-Extra: drivers-vector-amazon-opensearch
Requires-Dist: boto3>=1.34.119; extra == 'drivers-vector-amazon-opensearch'
Requires-Dist: opensearch-py>=2.3.1; extra == 'drivers-vector-amazon-opensearch'
Provides-Extra: drivers-vector-astra-db
Requires-Dist: astrapy>=2.0; extra == 'drivers-vector-astra-db'
Provides-Extra: drivers-vector-marqo
Requires-Dist: marqo>=3.9.2; extra == 'drivers-vector-marqo'
Provides-Extra: drivers-vector-mongodb
Requires-Dist: pymongo>=4.8.0; extra == 'drivers-vector-mongodb'
Provides-Extra: drivers-vector-opensearch
Requires-Dist: opensearch-py>=2.3.1; extra == 'drivers-vector-opensearch'
Provides-Extra: drivers-vector-pgai
Requires-Dist: sqlalchemy>=2.0.31; extra == 'drivers-vector-pgai'
Provides-Extra: drivers-vector-pgvector
Requires-Dist: pgvector>=0.3.4; extra == 'drivers-vector-pgvector'
Requires-Dist: psycopg2-binary>=2.9.9; extra == 'drivers-vector-pgvector'
Requires-Dist: sqlalchemy>=2.0.31; extra == 'drivers-vector-pgvector'
Provides-Extra: drivers-vector-pinecone
Requires-Dist: pinecone>=6.0.1; extra == 'drivers-vector-pinecone'
Provides-Extra: drivers-vector-qdrant
Requires-Dist: qdrant-client>=1.10.1; extra == 'drivers-vector-qdrant'
Provides-Extra: drivers-vector-redis
Requires-Dist: redis>=5.1.0; extra == 'drivers-vector-redis'
Provides-Extra: drivers-web-scraper-markdownify
Requires-Dist: beautifulsoup4>=4.12.3; extra == 'drivers-web-scraper-markdownify'
Requires-Dist: markdownify>=1.0.0; extra == 'drivers-web-scraper-markdownify'
Requires-Dist: playwright>=1.42; extra == 'drivers-web-scraper-markdownify'
Provides-Extra: drivers-web-scraper-trafilatura
Requires-Dist: trafilatura>=2.0; extra == 'drivers-web-scraper-trafilatura'
Provides-Extra: drivers-web-search-duckduckgo
Requires-Dist: duckduckgo-search>=7.0.1; extra == 'drivers-web-search-duckduckgo'
Provides-Extra: drivers-web-search-exa
Requires-Dist: exa-py>=1.1.4; extra == 'drivers-web-search-exa'
Provides-Extra: drivers-web-search-tavily
Requires-Dist: tavily-python>=0.5.0; extra == 'drivers-web-search-tavily'
Provides-Extra: loaders-email
Requires-Dist: mail-parser>=4.0.0; extra == 'loaders-email'
Provides-Extra: loaders-image
Requires-Dist: pillow>=11.0.0; extra == 'loaders-image'
Provides-Extra: loaders-pdf
Requires-Dist: pypdf>=5.0.1; extra == 'loaders-pdf'
Provides-Extra: loaders-sql
Requires-Dist: sqlalchemy>=2.0.31; extra == 'loaders-sql'
